{
  "latestVersion": "1.2.1",
  "title": "Prayer Controller Pro v1.2.1",
  "notes": "This release adds the official Prayer Controller Pro identity across the repository and app, including the app icon, tray icon, branded header, publisher metadata, and a structured About window with version, publisher, repository, and update feed details.",
  "downloadUrl": "https://raw.githubusercontent.com/iiiYar/PrayerControllerPro/main/downloads/PrayerControllerPro-v1.2.1-win-x64.zip",
  "releaseUrl": "https://github.com/iiiYar/PrayerControllerPro/tree/v1.2.1",
  "sha256": "2809A390C9A89B897CF3D0CEFF9C6617830C996A4F6865D9250430CADCD0223C",
  "mandatory": false
}
